azkar_local_client/__init__.py
azkar_local_client/azkar_data.json
azkar_local_client/client.py
azkar_local_client-0.1.0.dist-info/METADATA
azkar_local_client-0.1.0.dist-info/WHEEL
azkar_local_client-0.1.0.dist-info/top_level.txt
azkar_local_client-0.1.0.dist-info/RECORD
